__init__.py
pyclipboard/__init__.py
pyclipboard-1.0.dist-info/LICENSE
pyclipboard-1.0.dist-info/METADATA
pyclipboard-1.0.dist-info/WHEEL
pyclipboard-1.0.dist-info/top_level.txt
pyclipboard-1.0.dist-info/RECORD
