Metadata-Version: 2.1
Name: pyclipboard
Version: 1.0
Summary: A all-in-one tool for clipboard management for MAC OS only.
Author-email: Fu Ruochen <mail.by.ray@gmail.com>
Project-URL: Homepage, https://github.com/RuochenFu21/pyclipboard
Project-URL: Bug Tracker, https://github.com/RuochenFu21/pyclipboard/issues
Classifier: Programming Language :: Python :: 3
Classifier: License :: OSI Approved :: MIT License
Classifier: Operating System :: MacOS
Requires-Python: >=3.8
License-File: LICENSE
Requires-Dist: pillow (>=1.0)
Requires-Dist: pyobjc (>=8.0)
